pypocket/__init__.py
pypocket/auth.py
pypocket/html.py
pypocket/pocket.py
pypocket/pocket_api_endpoints.py
pypocket/pocket_dataclass.py
pypocket/test/__init__.py
pypocket/test/auth_test.py
pypocket/test/html_test.py
pypocket/test/pocket_test.py
pypocket/test/utils_test.py
pypocket/utils.py
pypocket-0.2.0.dist-info/LICENSE
pypocket-0.2.0.dist-info/WHEEL
pypocket-0.2.0.dist-info/METADATA
pypocket-0.2.0.dist-info/RECORD
