Metadata-Version: 2.1
Name: pypocket
Version: 0.2.0
Summary: A Python wrapper for GetPocket
Home-page: https://github.com/e-alizadeh/PyPocket
License: MIT
Keywords: GetPocket,pocket,wrapper
Author: Essi Alizadeh
Author-email: pypocket@ealizadeh.com
Requires-Python: >=3.7.1,<4.0.0
Classifier: License :: OSI Approved :: MIT License
Classifier: Programming Language :: Python :: 3
Classifier: Programming Language :: Python :: 3.8
Classifier: Programming Language :: Python :: 3.9
Requires-Dist: dominate (>=2.6.0,<3.0.0)
Requires-Dist: requests (>=2.25.1,<3.0.0)
Project-URL: Repository, https://github.com/e-alizadeh/PyPocket
